{
  "openapi": "3.0.1",
  "info": {
    "title": "openAPI",
    "version": "v1"
  },
  "paths": {
    "/api/v1/grudge": {
      "post": {
        "tags": [
          "Book"
        ],
        "responses": {
          "200": {
            "description": "OK"
          }
        }
      },
      "get": {
        "tags": [
          "Book"
        ],
        "responses": {
          "200": {
            "description": "OK"
          }
        }
      }
    },
    "/api/v1/grudge/{id}": {
      "put": {
        "tags": [
          "Book"
        ],
        "parameters": [
          {
            "name": "id",
            "in": "path",
            "required": true,
            "schema": {
              "type": "string"
            }
          }
        ],
        "responses": {
          "200": {
            "description": "OK"
          }
        }
      },
      "get": {
        "tags": [
          "Book"
        ],
        "parameters": [
          {
            "name": "id",
            "in": "path",
            "required": true,
            "schema": {
              "type": "string"
            }
          }
        ],
        "responses": {
          "200": {
            "description": "OK"
          }
        }
      },
      "delete": {
        "tags": [
          "Book"
        ],
        "parameters": [
          {
            "name": "id",
            "in": "path",
            "required": true,
            "schema": {
              "type": "string"
            }
          }
        ],
        "responses": {
          "200": {
            "description": "OK"
          }
        }
      }
    },
    "/api/v1/auth/signup": {
      "post": {
        "tags": [
          "DwarvenAuthentication"
        ],
        "parameters": [
          {
            "name": "username",
            "in": "query",
            "schema": {
              "type": "string"
            }
          }
        ],
        "responses": {
          "200": {
            "description": "OK"
          }
        }
      }
    },
    "/api/v1/auth/signin": {
      "post": {
        "tags": [
          "DwarvenAuthentication"
        ],
        "parameters": [
          {
            "name": "username",
            "in": "query",
            "schema": {
              "type": "string"
            }
          }
        ],
        "responses": {
          "200": {
            "description": "OK"
          }
        }
      }
    }
  },
  "components": {
    "securitySchemes": {
      "bearerAuth": {
        "type": "http",
        "description": "JWT Authorization header using the Bearer scheme.",
        "scheme": "bearer",
        "bearerFormat": "JWT"
      }
    }
  },
  "security": [
    {
      "bearerAuth": [ ]
    }
  ]
}